ev_manager/__init__.py
ev_manager/ev_manager.py
ev_manager/event.py
ev_manager-0.1.0.dist-info/LICENSE
ev_manager-0.1.0.dist-info/METADATA
ev_manager-0.1.0.dist-info/WHEEL
ev_manager-0.1.0.dist-info/top_level.txt
ev_manager-0.1.0.dist-info/RECORD
