Metadata-Version: 2.1
Name: ev-manager
Version: 0.1.0
Summary: Bind functions to events that can be called from any other script at any time.
Home-page: https://github.com/nils-soderman/ev-manager
Author: Nils Soderman
Keywords: event,manager,bind,subscribe,fire,function,callback,emit
Classifier: Programming Language :: Python :: 3
Requires-Python: >=3.7
License-File: LICENSE
